sphinxcontrib_asciiart-1.1.3-py3.13-nspkg.pth
sphinxcontrib/asciiart.css
sphinxcontrib/asciiart.py
sphinxcontrib_asciiart-1.1.3.dist-info/METADATA
sphinxcontrib_asciiart-1.1.3.dist-info/WHEEL
sphinxcontrib_asciiart-1.1.3.dist-info/namespace_packages.txt
sphinxcontrib_asciiart-1.1.3.dist-info/top_level.txt
sphinxcontrib_asciiart-1.1.3.dist-info/RECORD
