Metadata-Version: 2.4
Name: sphinxcontrib-asciiart
Version: 1.1.3
Summary: Sphinx extension asciiart.
Home-page: https://pypi.org/project/sphinxcontrib-asciiart/
Author: Yongping Guo
Author-email: Yongping Guo <guoyoooping@163.com>
License: BSD
Keywords: sphinx,sphinxcontrib,asciiart
Platform: any
Requires-Dist: Pillow>=3.0.0
Dynamic: author
Dynamic: home-page
Dynamic: platform
